{
  "run_metadata": {
    "generated_at_utc": "2026-07-05T20:39:15.463672+00:00",
    "top_n": 50,
    "time_period": "MONTH",
    "order_by": "PNL",
    "min_position_usd_filter": 1.0,
    "active_only": true
  },
  "summary": {
    "traders_requested": 50,
    "traders_with_data": 50,
    "traders_failed_or_hidden": 0,
    "total_open_positions_analyzed": 1196,
    "unique_markets_represented": 609
  },
  "top_5_consensus_markets": [
    {
      "market_title": "Brazil vs. Norway: O/U 2.5",
      "condition_id": "0xf134b5d6d31ea59fe65cb22961ec1120e41a2451ef9311d6b750d6638a1c9322",
      "event_slug": "fifwc-bra-nor-2026-07-05-more-markets",
      "favored_outcome": "Under",
      "num_top50_traders": 11,
      "total_combined_usd": 2141667.87,
      "backers": [
        "0x25d3d4e4",
        "0x2c335066FE58fe9237c3d3Dc7b275C2a034a0563-1759935795465",
        "1two1two",
        "NO-GOD-PLEASE-NO",
        "RISK-IS-NEVER-OK",
        "RN1",
        "VPenguin",
        "hot2trot",
        "maz26",
        "ndb1",
        "swisstony"
      ]
    },
    {
      "market_title": "Brazil vs. Norway: O/U 2.5",
      "condition_id": "0xf134b5d6d31ea59fe65cb22961ec1120e41a2451ef9311d6b750d6638a1c9322",
      "event_slug": "fifwc-bra-nor-2026-07-05-more-markets",
      "favored_outcome": "Over",
      "num_top50_traders": 11,
      "total_combined_usd": 384321.54,
      "backers": [
        "0x3DFb153c197D4C19D3B31c1ecD2c7B6860eeabAf-1722957908185",
        "CandleHammerDrums",
        "Jokerxing7",
        "RN1",
        "Woaifacai",
        "easymoney9",
        "lookaon",
        "mooseborzoi",
        "phonesculptor",
        "shijiebeifacai",
        "swisstony"
      ]
    },
    {
      "market_title": "Will Brazil win on 2026-07-05?",
      "condition_id": "0x2a0e8ce7c309ec8015c4c721dec574ff100b0512ef412a54bb733dc5bef740dc",
      "event_slug": "fifwc-bra-nor-2026-07-05",
      "favored_outcome": "Yes",
      "num_top50_traders": 10,
      "total_combined_usd": 802449.28,
      "backers": [
        "CandleHammerDrums",
        "Oneger",
        "RN1",
        "Woaifacai",
        "bbb17367162806",
        "easymoney9",
        "mooseborzoi",
        "needheal",
        "swisstony",
        "zhuz632"
      ]
    },
    {
      "market_title": "Will Brazil vs. Norway end in a draw?",
      "condition_id": "0x87030106adba59ce8ef007955073623da31f15fdf4655b96cf033fb9e57df694",
      "event_slug": "fifwc-bra-nor-2026-07-05",
      "favored_outcome": "No",
      "num_top50_traders": 8,
      "total_combined_usd": 419195.3,
      "backers": [
        "0x2c335066FE58fe9237c3d3Dc7b275C2a034a0563-1759935795465",
        "0x53757615",
        "NO-GOD-PLEASE-NO",
        "RN1",
        "bbb17367162806",
        "easymoney9",
        "mooseborzoi",
        "umeax"
      ]
    },
    {
      "market_title": "Will Spain win the 2026 FIFA World Cup?",
      "condition_id": "0x7976b8dbacf9077eb1453a62bcefd6ab2df199acd28aad276ff0d920d6992892",
      "event_slug": "world-cup-winner",
      "favored_outcome": "Yes",
      "num_top50_traders": 8,
      "total_combined_usd": 374198.22,
      "backers": [
        "0x2c335066FE58fe9237c3d3Dc7b275C2a034a0563-1759935795465",
        "0x53757615",
        "Crystiano",
        "Jsram",
        "Q96s3kwozynxpau",
        "cnyek",
        "mooseborzoi",
        "shijiebeifacai"
      ]
    }
  ],
  "pure_count_consensus": [
    {
      "condition_id": "0xf134b5d6d31ea59fe65cb22961ec1120e41a2451ef9311d6b750d6638a1c9322",
      "market_title": "Brazil vs. Norway: O/U 2.5",
      "event_slug": "fifwc-bra-nor-2026-07-05-more-markets",
      "outcome": "Under",
      "trader_count": 11,
      "total_usd": 2141667.8743,
      "traders": [
        "0x25d3d4e4",
        "0x2c335066FE58fe9237c3d3Dc7b275C2a034a0563-1759935795465",
        "1two1two",
        "NO-GOD-PLEASE-NO",
        "RISK-IS-NEVER-OK",
        "RN1",
        "VPenguin",
        "hot2trot",
        "maz26",
        "ndb1",
        "swisstony"
      ],
      "cur_price": 0.6332,
      "avg_entry": 0.4492,
      "entry_gap_cents": -18.4,
      "opp_traders": 11,
      "net_traders": 0,
      "conflicted": true,
      "liquidity_usd": 226044.44,
      "volume_24h": 6147900.02,
      "spread": 0.01,
      "best_ask": 0.37,
      "best_bid": 0.36,
      "net_prev": null,
      "net_delta": null,
      "is_new": true
    },
    {
      "condition_id": "0xf134b5d6d31ea59fe65cb22961ec1120e41a2451ef9311d6b750d6638a1c9322",
      "market_title": "Brazil vs. Norway: O/U 2.5",
      "event_slug": "fifwc-bra-nor-2026-07-05-more-markets",
      "outcome": "Over",
      "trader_count": 11,
      "total_usd": 384321.5355,
      "traders": [
        "0x3DFb153c197D4C19D3B31c1ecD2c7B6860eeabAf-1722957908185",
        "CandleHammerDrums",
        "Jokerxing7",
        "RN1",
        "Woaifacai",
        "easymoney9",
        "lookaon",
        "mooseborzoi",
        "phonesculptor",
        "shijiebeifacai",
        "swisstony"
      ],
      "cur_price": 0.3659,
      "avg_entry": 0.5335,
      "entry_gap_cents": 16.8,
      "opp_traders": 11,
      "net_traders": 0,
      "conflicted": true,
      "liquidity_usd": 226044.44,
      "volume_24h": 6147900.02,
      "spread": 0.01,
      "best_ask": 0.37,
      "best_bid": 0.36,
      "net_prev": null,
      "net_delta": null,
      "is_new": true
    },
    {
      "condition_id": "0x2a0e8ce7c309ec8015c4c721dec574ff100b0512ef412a54bb733dc5bef740dc",
      "market_title": "Will Brazil win on 2026-07-05?",
      "event_slug": "fifwc-bra-nor-2026-07-05",
      "outcome": "Yes",
      "trader_count": 10,
      "total_usd": 802449.2819,
      "traders": [
        "CandleHammerDrums",
        "Oneger",
        "RN1",
        "Woaifacai",
        "bbb17367162806",
        "easymoney9",
        "mooseborzoi",
        "needheal",
        "swisstony",
        "zhuz632"
      ],
      "cur_price": 0.525,
      "avg_entry": 0.5471,
      "entry_gap_cents": 2.2,
      "opp_traders": 6,
      "net_traders": 4,
      "conflicted": true,
      "liquidity_usd": 485436.09,
      "volume_24h": 8750872.5,
      "spread": 0.01,
      "best_ask": 0.53,
      "best_bid": 0.52,
      "net_prev": null,
      "net_delta": null,
      "is_new": true
    },
    {
      "condition_id": "0x87030106adba59ce8ef007955073623da31f15fdf4655b96cf033fb9e57df694",
      "market_title": "Will Brazil vs. Norway end in a draw?",
      "event_slug": "fifwc-bra-nor-2026-07-05",
      "outcome": "No",
      "trader_count": 8,
      "total_usd": 419195.3029,
      "traders": [
        "0x2c335066FE58fe9237c3d3Dc7b275C2a034a0563-1759935795465",
        "0x53757615",
        "NO-GOD-PLEASE-NO",
        "RN1",
        "bbb17367162806",
        "easymoney9",
        "mooseborzoi",
        "umeax"
      ],
      "cur_price": 0.715,
      "avg_entry": 0.7368,
      "entry_gap_cents": 2.2,
      "opp_traders": 4,
      "net_traders": 4,
      "conflicted": true,
      "liquidity_usd": 361364.5,
      "volume_24h": 1821177.13,
      "spread": 0.01,
      "best_ask": 0.72,
      "best_bid": 0.71,
      "net_prev": null,
      "net_delta": null,
      "is_new": true
    },
    {
      "condition_id": "0x7976b8dbacf9077eb1453a62bcefd6ab2df199acd28aad276ff0d920d6992892",
      "market_title": "Will Spain win the 2026 FIFA World Cup?",
      "event_slug": "world-cup-winner",
      "outcome": "Yes",
      "trader_count": 8,
      "total_usd": 374198.2186,
      "traders": [
        "0x2c335066FE58fe9237c3d3Dc7b275C2a034a0563-1759935795465",
        "0x53757615",
        "Crystiano",
        "Jsram",
        "Q96s3kwozynxpau",
        "cnyek",
        "mooseborzoi",
        "shijiebeifacai"
      ],
      "cur_price": 0.1245,
      "avg_entry": 0.1137,
      "entry_gap_cents": -1.1,
      "opp_traders": 0,
      "net_traders": 8,
      "conflicted": false,
      "liquidity_usd": 4629120.64,
      "volume_24h": 1289323.15,
      "spread": 0.0,
      "best_ask": 0.125,
      "best_bid": 0.124,
      "net_prev": 8.0,
      "net_delta": 0.0,
      "is_new": false
    },
    {
      "condition_id": "0x9b6fef249040fd17e9c107955b37ac2c3e923509b6b0ff01cc463a331ddeb894",
      "market_title": "Will France win the 2026 FIFA World Cup?",
      "event_slug": "world-cup-winner",
      "outcome": "Yes",
      "trader_count": 7,
      "total_usd": 938468.3232,
      "traders": [
        "0x2c335066FE58fe9237c3d3Dc7b275C2a034a0563-1759935795465",
        "0x53757615",
        "CandleHammerDrums",
        "Jsram",
        "Q96s3kwozynxpau",
        "mooseborzoi",
        "shijiebeifacai"
      ],
      "cur_price": 0.3454,
      "avg_entry": 0.1826,
      "entry_gap_cents": -16.3,
      "opp_traders": 0,
      "net_traders": 7,
      "conflicted": false,
      "liquidity_usd": 3601432.15,
      "volume_24h": 1491887.55,
      "spread": 0.0,
      "best_ask": 0.346,
      "best_bid": 0.345,
      "net_prev": 8.0,
      "net_delta": -1.0,
      "is_new": false
    },
    {
      "condition_id": "0x94e50623d3cfdc1256e16ff372062d42c282bec8af620bb732a19fb4b0dce580",
      "market_title": "Mexico vs. England: Team to Advance",
      "event_slug": "fifwc-mex-eng-2026-07-05-more-markets",
      "outcome": "Mexico",
      "trader_count": 6,
      "total_usd": 1685071.467,
      "traders": [
        "0x2c335066FE58fe9237c3d3Dc7b275C2a034a0563-1759935795465",
        "Crystiano",
        "RN1",
        "ramadamaramadam",
        "sleepy-panda",
        "surfandturf"
      ],
      "cur_price": 0.485,
      "avg_entry": 0.474,
      "entry_gap_cents": -1.1,
      "opp_traders": 5,
      "net_traders": 1,
      "conflicted": true,
      "liquidity_usd": 3013004.2,
      "volume_24h": 6771019.64,
      "spread": 0.01,
      "best_ask": 0.49,
      "best_bid": 0.48,
      "net_prev": 1.0,
      "net_delta": 0.0,
      "is_new": false
    },
    {
      "condition_id": "0x2a0e8ce7c309ec8015c4c721dec574ff100b0512ef412a54bb733dc5bef740dc",
      "market_title": "Will Brazil win on 2026-07-05?",
      "event_slug": "fifwc-bra-nor-2026-07-05",
      "outcome": "No",
      "trader_count": 6,
      "total_usd": 1328541.0877,
      "traders": [
        "0xC41D736bDed9ED1acCD6A44235039266219774fD-1777101352681",
        "Qpkwks",
        "RN1",
        "maz26",
        "swisstony",
        "umeax"
      ],
      "cur_price": 0.475,
      "avg_entry": 0.4531,
      "entry_gap_cents": -2.2,
      "opp_traders": 10,
      "net_traders": -4,
      "conflicted": true,
      "liquidity_usd": 485436.09,
      "volume_24h": 8750872.5,
      "spread": 0.01,
      "best_ask": 0.48,
      "best_bid": 0.47,
      "net_prev": null,
      "net_delta": null,
      "is_new": true
    },
    {
      "condition_id": "0x99f0c39e4235d840bd25d2c229b2cda57cc087b6b8c2780f804fffeed0d0c628",
      "market_title": "Will England win on 2026-07-05?",
      "event_slug": "fifwc-mex-eng-2026-07-05",
      "outcome": "No",
      "trader_count": 6,
      "total_usd": 1192481.1431,
      "traders": [
        "0x2c335066FE58fe9237c3d3Dc7b275C2a034a0563-1759935795465",
        "Kch-Temp",
        "mooseborzoi",
        "ramadamaramadam",
        "swisstony",
        "weflyhigh"
      ],
      "cur_price": 0.625,
      "avg_entry": 0.6111,
      "entry_gap_cents": -1.4,
      "opp_traders": 3,
      "net_traders": 3,
      "conflicted": true,
      "liquidity_usd": 2863178.96,
      "volume_24h": 1715985.69,
      "spread": 0.01,
      "best_ask": 0.63,
      "best_bid": 0.62,
      "net_prev": 2.0,
      "net_delta": 1.0,
      "is_new": false
    },
    {
      "condition_id": "0xe6f040d202cefefe47bdc9d192303905418223fec440f96eb2abe98f3b701bd4",
      "market_title": "Will Norway win on 2026-07-05?",
      "event_slug": "fifwc-bra-nor-2026-07-05",
      "outcome": "No",
      "trader_count": 6,
      "total_usd": 914583.3142,
      "traders": [
        "0x2c335066FE58fe9237c3d3Dc7b275C2a034a0563-1759935795465",
        "MD14",
        "RN1",
        "balekadyr",
        "shijiebeifacai",
        "swisstony"
      ],
      "cur_price": 0.8149,
      "avg_entry": 0.8006,
      "entry_gap_cents": -1.4,
      "opp_traders": 4,
      "net_traders": 2,
      "conflicted": true,
      "liquidity_usd": 476231.23,
      "volume_24h": 4102794.02,
      "spread": 0.01,
      "best_ask": 0.82,
      "best_bid": 0.81,
      "net_prev": null,
      "net_delta": null,
      "is_new": true
    }
  ],
  "capital_weighted_consensus": [
    {
      "condition_id": "0x0c4cd2055d6ea89354ffddc55d6dbcef9355748112ea952fc925f3db6a5c457f",
      "market_title": "Will Argentina win the 2026 FIFA World Cup?",
      "event_slug": "world-cup-winner",
      "outcome": "No",
      "total_usd": 3666576.7146,
      "trader_count": 2,
      "traders": [
        "ndb1",
        "needheal"
      ],
      "cur_price": 0.8265,
      "avg_entry": 0.8838,
      "entry_gap_cents": 5.7,
      "opp_traders": 6,
      "net_traders": -4,
      "conflicted": true,
      "liquidity_usd": 1691570.89,
      "volume_24h": 1576799.14,
      "spread": 0.0,
      "best_ask": 0.827,
      "best_bid": 0.826,
      "net_prev": -5.0,
      "net_delta": 1.0,
      "is_new": false
    },
    {
      "condition_id": "0xf134b5d6d31ea59fe65cb22961ec1120e41a2451ef9311d6b750d6638a1c9322",
      "market_title": "Brazil vs. Norway: O/U 2.5",
      "event_slug": "fifwc-bra-nor-2026-07-05-more-markets",
      "outcome": "Under",
      "total_usd": 2141667.8743,
      "trader_count": 11,
      "traders": [
        "0x25d3d4e4",
        "0x2c335066FE58fe9237c3d3Dc7b275C2a034a0563-1759935795465",
        "1two1two",
        "NO-GOD-PLEASE-NO",
        "RISK-IS-NEVER-OK",
        "RN1",
        "VPenguin",
        "hot2trot",
        "maz26",
        "ndb1",
        "swisstony"
      ],
      "cur_price": 0.6332,
      "avg_entry": 0.4492,
      "entry_gap_cents": -18.4,
      "opp_traders": 11,
      "net_traders": 0,
      "conflicted": true,
      "liquidity_usd": 226044.44,
      "volume_24h": 6147900.02,
      "spread": 0.01,
      "best_ask": 0.37,
      "best_bid": 0.36,
      "net_prev": null,
      "net_delta": null,
      "is_new": true
    },
    {
      "condition_id": "0x94e50623d3cfdc1256e16ff372062d42c282bec8af620bb732a19fb4b0dce580",
      "market_title": "Mexico vs. England: Team to Advance",
      "event_slug": "fifwc-mex-eng-2026-07-05-more-markets",
      "outcome": "Mexico",
      "total_usd": 1685071.467,
      "trader_count": 6,
      "traders": [
        "0x2c335066FE58fe9237c3d3Dc7b275C2a034a0563-1759935795465",
        "Crystiano",
        "RN1",
        "ramadamaramadam",
        "sleepy-panda",
        "surfandturf"
      ],
      "cur_price": 0.485,
      "avg_entry": 0.474,
      "entry_gap_cents": -1.1,
      "opp_traders": 5,
      "net_traders": 1,
      "conflicted": true,
      "liquidity_usd": 3013004.2,
      "volume_24h": 6771019.64,
      "spread": 0.01,
      "best_ask": 0.49,
      "best_bid": 0.48,
      "net_prev": 1.0,
      "net_delta": 0.0,
      "is_new": false
    },
    {
      "condition_id": "0x2a0e8ce7c309ec8015c4c721dec574ff100b0512ef412a54bb733dc5bef740dc",
      "market_title": "Will Brazil win on 2026-07-05?",
      "event_slug": "fifwc-bra-nor-2026-07-05",
      "outcome": "No",
      "total_usd": 1328541.0877,
      "trader_count": 6,
      "traders": [
        "0xC41D736bDed9ED1acCD6A44235039266219774fD-1777101352681",
        "Qpkwks",
        "RN1",
        "maz26",
        "swisstony",
        "umeax"
      ],
      "cur_price": 0.475,
      "avg_entry": 0.4531,
      "entry_gap_cents": -2.2,
      "opp_traders": 10,
      "net_traders": -4,
      "conflicted": true,
      "liquidity_usd": 485436.09,
      "volume_24h": 8750872.5,
      "spread": 0.01,
      "best_ask": 0.48,
      "best_bid": 0.47,
      "net_prev": null,
      "net_delta": null,
      "is_new": true
    },
    {
      "condition_id": "0x94e50623d3cfdc1256e16ff372062d42c282bec8af620bb732a19fb4b0dce580",
      "market_title": "Mexico vs. England: Team to Advance",
      "event_slug": "fifwc-mex-eng-2026-07-05-more-markets",
      "outcome": "England",
      "total_usd": 1302256.5884,
      "trader_count": 5,
      "traders": [
        "0x2c335066FE58fe9237c3d3Dc7b275C2a034a0563-1759935795465",
        "0x3DFb153c197D4C19D3B31c1ecD2c7B6860eeabAf-1722957908185",
        "eyepredicts",
        "ndb1",
        "zhuz632"
      ],
      "cur_price": 0.515,
      "avg_entry": 0.5281,
      "entry_gap_cents": 1.3,
      "opp_traders": 6,
      "net_traders": -1,
      "conflicted": true,
      "liquidity_usd": 3013004.2,
      "volume_24h": 6771019.64,
      "spread": 0.01,
      "best_ask": 0.49,
      "best_bid": 0.48,
      "net_prev": -1.0,
      "net_delta": 0.0,
      "is_new": false
    },
    {
      "condition_id": "0x99f0c39e4235d840bd25d2c229b2cda57cc087b6b8c2780f804fffeed0d0c628",
      "market_title": "Will England win on 2026-07-05?",
      "event_slug": "fifwc-mex-eng-2026-07-05",
      "outcome": "No",
      "total_usd": 1192481.1431,
      "trader_count": 6,
      "traders": [
        "0x2c335066FE58fe9237c3d3Dc7b275C2a034a0563-1759935795465",
        "Kch-Temp",
        "mooseborzoi",
        "ramadamaramadam",
        "swisstony",
        "weflyhigh"
      ],
      "cur_price": 0.625,
      "avg_entry": 0.6111,
      "entry_gap_cents": -1.4,
      "opp_traders": 3,
      "net_traders": 3,
      "conflicted": true,
      "liquidity_usd": 2863178.96,
      "volume_24h": 1715985.69,
      "spread": 0.01,
      "best_ask": 0.63,
      "best_bid": 0.62,
      "net_prev": 2.0,
      "net_delta": 1.0,
      "is_new": false
    },
    {
      "condition_id": "0x9b6fef249040fd17e9c107955b37ac2c3e923509b6b0ff01cc463a331ddeb894",
      "market_title": "Will France win the 2026 FIFA World Cup?",
      "event_slug": "world-cup-winner",
      "outcome": "Yes",
      "total_usd": 938468.3232,
      "trader_count": 7,
      "traders": [
        "0x2c335066FE58fe9237c3d3Dc7b275C2a034a0563-1759935795465",
        "0x53757615",
        "CandleHammerDrums",
        "Jsram",
        "Q96s3kwozynxpau",
        "mooseborzoi",
        "shijiebeifacai"
      ],
      "cur_price": 0.3454,
      "avg_entry": 0.1826,
      "entry_gap_cents": -16.3,
      "opp_traders": 0,
      "net_traders": 7,
      "conflicted": false,
      "liquidity_usd": 3601432.15,
      "volume_24h": 1491887.55,
      "spread": 0.0,
      "best_ask": 0.346,
      "best_bid": 0.345,
      "net_prev": 8.0,
      "net_delta": -1.0,
      "is_new": false
    },
    {
      "condition_id": "0xe6f040d202cefefe47bdc9d192303905418223fec440f96eb2abe98f3b701bd4",
      "market_title": "Will Norway win on 2026-07-05?",
      "event_slug": "fifwc-bra-nor-2026-07-05",
      "outcome": "No",
      "total_usd": 914583.3142,
      "trader_count": 6,
      "traders": [
        "0x2c335066FE58fe9237c3d3Dc7b275C2a034a0563-1759935795465",
        "MD14",
        "RN1",
        "balekadyr",
        "shijiebeifacai",
        "swisstony"
      ],
      "cur_price": 0.8149,
      "avg_entry": 0.8006,
      "entry_gap_cents": -1.4,
      "opp_traders": 4,
      "net_traders": 2,
      "conflicted": true,
      "liquidity_usd": 476231.23,
      "volume_24h": 4102794.02,
      "spread": 0.01,
      "best_ask": 0.82,
      "best_bid": 0.81,
      "net_prev": null,
      "net_delta": null,
      "is_new": true
    },
    {
      "condition_id": "0x2a0e8ce7c309ec8015c4c721dec574ff100b0512ef412a54bb733dc5bef740dc",
      "market_title": "Will Brazil win on 2026-07-05?",
      "event_slug": "fifwc-bra-nor-2026-07-05",
      "outcome": "Yes",
      "total_usd": 802449.2819,
      "trader_count": 10,
      "traders": [
        "CandleHammerDrums",
        "Oneger",
        "RN1",
        "Woaifacai",
        "bbb17367162806",
        "easymoney9",
        "mooseborzoi",
        "needheal",
        "swisstony",
        "zhuz632"
      ],
      "cur_price": 0.525,
      "avg_entry": 0.5471,
      "entry_gap_cents": 2.2,
      "opp_traders": 6,
      "net_traders": 4,
      "conflicted": true,
      "liquidity_usd": 485436.09,
      "volume_24h": 8750872.5,
      "spread": 0.01,
      "best_ask": 0.53,
      "best_bid": 0.52,
      "net_prev": null,
      "net_delta": null,
      "is_new": true
    },
    {
      "condition_id": "0xa1299a3672399edbf7c3013af05a886b9ec3034959b36ecb9171c3747a937bf0",
      "market_title": "Exact Score: Brazil 2 - 1 Norway?",
      "event_slug": "fifwc-bra-nor-2026-07-05-exact-score",
      "outcome": "No",
      "total_usd": 696732.8985,
      "trader_count": 3,
      "traders": [
        "0x2c335066FE58fe9237c3d3Dc7b275C2a034a0563-1759935795465",
        "RN1",
        "swisstony"
      ],
      "cur_price": 0.895,
      "avg_entry": 0.8763,
      "entry_gap_cents": -1.9,
      "opp_traders": 2,
      "net_traders": 1,
      "conflicted": true,
      "liquidity_usd": 57821.16,
      "volume_24h": 1699082.31,
      "spread": 0.01,
      "best_ask": 0.9,
      "best_bid": 0.89,
      "net_prev": null,
      "net_delta": null,
      "is_new": true
    }
  ],
  "high_conviction_divergence": [
    {
      "condition_id": "0xe81ec0ca7357d9e91e9b95e1ecf60606f8b1686290464758b9a3595aeae11a1a",
      "market_title": "Brazil vs. Norway: Both Teams to Score",
      "event_slug": "fifwc-bra-nor-2026-07-05-more-markets",
      "outcome": "Yes",
      "conviction_traders": 3,
      "score_raw": 22.898814,
      "avg_cost_pct": 30.26,
      "avg_skill": 0.216,
      "total_usd": 458452.9494,
      "traders": [
        "Crystiano",
        "RN1",
        "mooseborzoi"
      ],
      "conviction_score": 100.0,
      "cur_price": 0.445,
      "avg_entry": 0.6193,
      "entry_gap_cents": 17.4,
      "opp_traders": 4,
      "net_traders": -1,
      "conflicted": true,
      "liquidity_usd": 132403.94,
      "volume_24h": 3852826.35,
      "spread": 0.01,
      "best_ask": 0.45,
      "best_bid": 0.44,
      "net_prev": null,
      "net_delta": null,
      "is_new": true
    },
    {
      "condition_id": "0x0c4cd2055d6ea89354ffddc55d6dbcef9355748112ea952fc925f3db6a5c457f",
      "market_title": "Will Argentina win the 2026 FIFA World Cup?",
      "event_slug": "world-cup-winner",
      "outcome": "Yes",
      "conviction_traders": 3,
      "score_raw": 3.61444,
      "avg_cost_pct": 4.95,
      "avg_skill": 0.265,
      "total_usd": 245411.0418,
      "traders": [
        "0x53757615",
        "Q96s3kwozynxpau",
        "mooseborzoi"
      ],
      "conviction_score": 15.8,
      "cur_price": 0.1734,
      "avg_entry": 0.1568,
      "entry_gap_cents": -1.7,
      "opp_traders": 2,
      "net_traders": 1,
      "conflicted": true,
      "liquidity_usd": 1691570.89,
      "volume_24h": 1576799.14,
      "spread": 0.0,
      "best_ask": 0.174,
      "best_bid": 0.173,
      "net_prev": 5.0,
      "net_delta": -4.0,
      "is_new": false
    },
    {
      "condition_id": "0xa1299a3672399edbf7c3013af05a886b9ec3034959b36ecb9171c3747a937bf0",
      "market_title": "Exact Score: Brazil 2 - 1 Norway?",
      "event_slug": "fifwc-bra-nor-2026-07-05-exact-score",
      "outcome": "No",
      "conviction_traders": 3,
      "score_raw": 2.628654,
      "avg_cost_pct": 4.4,
      "avg_skill": 0.192,
      "total_usd": 696732.8985,
      "traders": [
        "0x2c335066FE58fe9237c3d3Dc7b275C2a034a0563-1759935795465",
        "RN1",
        "swisstony"
      ],
      "conviction_score": 11.5,
      "cur_price": 0.895,
      "avg_entry": 0.8763,
      "entry_gap_cents": -1.9,
      "opp_traders": 2,
      "net_traders": 1,
      "conflicted": true,
      "liquidity_usd": 57821.16,
      "volume_24h": 1699082.31,
      "spread": 0.01,
      "best_ask": 0.9,
      "best_bid": 0.89,
      "net_prev": null,
      "net_delta": null,
      "is_new": true
    },
    {
      "condition_id": "0xadeeee654dd8de80cc59a79eec20c280a3c409ebbaffae63b711eec3bb6c6373",
      "market_title": "Exact Score: Brazil 1 - 1 Norway?",
      "event_slug": "fifwc-bra-nor-2026-07-05-exact-score",
      "outcome": "No",
      "conviction_traders": 3,
      "score_raw": 1.668133,
      "avg_cost_pct": 2.86,
      "avg_skill": 0.192,
      "total_usd": 391964.6347,
      "traders": [
        "0x2c335066FE58fe9237c3d3Dc7b275C2a034a0563-1759935795465",
        "RN1",
        "swisstony"
      ],
      "conviction_score": 7.3,
      "cur_price": 0.855,
      "avg_entry": 0.8647,
      "entry_gap_cents": 1.0,
      "opp_traders": 2,
      "net_traders": 1,
      "conflicted": true,
      "liquidity_usd": 67650.41,
      "volume_24h": 798860.98,
      "spread": 0.01,
      "best_ask": 0.86,
      "best_bid": 0.85,
      "net_prev": null,
      "net_delta": null,
      "is_new": true
    }
  ],
  "failed_or_hidden_profiles": []
}